apolo_all/__init__.py
neuro_all-25.5.0.dist-info/LICENSE
neuro_all-25.5.0.dist-info/METADATA
neuro_all-25.5.0.dist-info/WHEEL
neuro_all-25.5.0.dist-info/entry_points.txt
neuro_all-25.5.0.dist-info/RECORD
