Metadata-Version: 2.3
Name: neuro-all
Version: 25.5.0
Summary: Combo package for installing all Apolo command line tools by 'pipx install apolo-all' command
License: Apache-2.0
Keywords: neu.ro,mlops,apolo
Author: Apolo Team
Author-email: dev@apolo.us
Requires-Python: >=3.9.0,<4.0.0
Classifier: Development Status :: 4 - Beta
Classifier: Environment :: Console
Classifier: Intended Audience :: Developers
Classifier: Intended Audience :: Information Technology
Classifier: Intended Audience :: Science/Research
Classifier: License :: OSI Approved :: Apache Software License
Classifier: Operating System :: OS Independent
Classifier: Programming Language :: Python :: 3
Classifier: Programming Language :: Python :: 3.9
Classifier: Programming Language :: Python :: 3.10
Classifier: Programming Language :: Python :: 3.11
Classifier: Programming Language :: Python :: 3.12
Classifier: Programming Language :: Python :: 3.13
Classifier: Topic :: Scientific/Engineering :: Artificial Intelligence
Classifier: Topic :: Software Development
Classifier: Topic :: Utilities
Requires-Dist: apolo-cli (==25.5.0)
Requires-Dist: apolo-extras (==24.10.0)
Requires-Dist: apolo-flow (==24.12.1)
Requires-Dist: apolo-sdk (==25.5.0)
Requires-Dist: certifi (==2025.4.26)
Project-URL: Homepage, https://apolo.us
Project-URL: Repository, https://github.com/neuro-inc/neuro-all
